slowarg/__init__.py
slowarg/main.py
slowarg/slowarg_snapshot.json
slowarg-0.2.3.data/scripts/slowarg
slowarg-0.2.3.dist-info/licenses/LICENSE
slowarg-0.2.3.dist-info/METADATA
slowarg-0.2.3.dist-info/WHEEL
slowarg-0.2.3.dist-info/top_level.txt
slowarg-0.2.3.dist-info/RECORD
